CPTtool/FEM_parser.py
CPTtool/__init__.py
CPTtool/bro.py
CPTtool/cpt_module.py
CPTtool/cpt_tool.py
CPTtool/gen_doc.py
CPTtool/inv_dist.py
CPTtool/log_handler.py
CPTtool/netcdf.py
CPTtool/robertson.py
CPTtool/tools_utils.py
CPTtool/shapefiles/Robertson.dbf
CPTtool/shapefiles/Robertson.shp
CPTtool/shapefiles/Robertson.shx
CPTtool-2.2.2.dist-info/LICENSE.txt
CPTtool-2.2.2.dist-info/METADATA
CPTtool-2.2.2.dist-info/WHEEL
CPTtool-2.2.2.dist-info/top_level.txt
CPTtool-2.2.2.dist-info/RECORD
